shalstab/__init__.py
shalstab/slope_analyzer.py
shalstab/training_data/__init__.py
shalstab/training_data/dem.tif
shalstab/training_data/geology.geojson
shalstab-1.0.3.dist-info/licenses/LICENSE
shalstab-1.0.3.dist-info/METADATA
shalstab-1.0.3.dist-info/WHEEL
shalstab-1.0.3.dist-info/top_level.txt
shalstab-1.0.3.dist-info/RECORD
