Metadata-Version: 2.4
Name: shalstab
Version: 1.0.3
Summary: Shallow Landsliding STABility (SHALSTAB) model for slope stability analysis
Home-page: https://github.com/federicogmz/shalstab
Author: Federico Gómez
Author-email: Federico Gómez <fjgomezc@eafit.edu.co>
License: GPL-3.0
Project-URL: Homepage, https://github.com/federicogmz/shalstab
Project-URL: Repository, https://github.com/federicogmz/shalstab.git
Project-URL: Documentation, https://github.com/federicogmz/shalstab/blob/main/README.md
Project-URL: Bug Reports, https://github.com/federicogmz/shalstab/issues
Keywords: shalstab,slope stability,landslide,geohazard,hydrology,geotechnical,gis,raster
Classifier: Development Status :: 5 - Production/Stable
Classifier: Intended Audience :: Science/Research
Classifier: License :: OSI Approved :: GNU General Public License v3 (GPLv3)
Classifier: Operating System :: OS Independent
Classifier: Programming Language :: Python :: 3
Classifier: Programming Language :: Python :: 3.8
Classifier: Programming Language :: Python :: 3.9
Classifier: Programming Language :: Python :: 3.10
Classifier: Programming Language :: Python :: 3.11
Classifier: Topic :: Scientific/Engineering :: GIS
Classifier: Topic :: Scientific/Engineering :: Hydrology
Classifier: Topic :: Scientific/Engineering :: Physics
Classifier: Topic :: Software Development :: Libraries :: Python Modules
Requires-Python: >=3.8
License-File: LICENSE
Requires-Dist: rasterio>=1.3.0
Requires-Dist: rioxarray>=0.13.0
Requires-Dist: numpy>=1.21.0
Requires-Dist: xarray>=2022.6.0
Requires-Dist: geopandas>=0.12.0
Requires-Dist: scipy>=1.9.0
Requires-Dist: pysheds>=0.3.0
Requires-Dist: matplotlib>=3.5.0
Requires-Dist: geocube>=0.3.0
Provides-Extra: dev
Requires-Dist: pytest>=7.0.0; extra == "dev"
Requires-Dist: pytest-cov>=4.0.0; extra == "dev"
Requires-Dist: black>=22.0.0; extra == "dev"
Requires-Dist: flake8>=5.0.0; extra == "dev"
Requires-Dist: sphinx>=5.0.0; extra == "dev"
Requires-Dist: sphinx-rtd-theme>=1.0.0; extra == "dev"
Requires-Dist: jupyter>=1.0.0; extra == "dev"
Requires-Dist: pre-commit>=2.20.0; extra == "dev"
Provides-Extra: all
Requires-Dist: pytest>=7.0.0; extra == "all"
Requires-Dist: pytest-cov>=4.0.0; extra == "all"
Requires-Dist: black>=22.0.0; extra == "all"
Requires-Dist: flake8>=5.0.0; extra == "all"
Requires-Dist: sphinx>=5.0.0; extra == "all"
Requires-Dist: sphinx-rtd-theme>=1.0.0; extra == "all"
Requires-Dist: jupyter>=1.0.0; extra == "all"
Requires-Dist: pre-commit>=2.20.0; extra == "all"
Dynamic: author
Dynamic: home-page
Dynamic: license-file
Dynamic: requires-python
